[
    {
        "label": "Overview",
        "style": "default",
        "rows": [
            [
                {
                    "name": "isActive"
                },
                {
                    "name": "sortOrder"
                }
            ],
            [
                {
                    "name": "name"
                }
            ],
            [
                {
                    "name": "description",
                    "fullWidth": true
                }
            ]
        ]
    }
]